.project-root
README.md
cpgpt/__init__.py
cpgpt/data/__init__.py
cpgpt/data/components/__init__.py
cpgpt/data/components/cpgpt_datasaver.py
cpgpt/data/components/cpgpt_dataset.py
cpgpt/data/components/dna_llm_embedder.py
cpgpt/data/components/illumina_methylation_prober.py
cpgpt/data/cpgpt_datamodule.py
cpgpt/eval.py
cpgpt/infer/__init__.py
cpgpt/infer/cpgpt_inferencer.py
cpgpt/log/__init__.py
cpgpt/log/utils.py
cpgpt/loss/__init__.py
cpgpt/loss/loss.py
cpgpt/model/__init__.py
cpgpt/model/components/__init__.py
cpgpt/model/components/model.py
cpgpt/model/components/modules.py
cpgpt/model/cpgpt_module.py
cpgpt/model/cpgpt_module_mortality.py
cpgpt/model/utils.py
cpgpt/train.py
cpgpt/trainer/__init__.py
cpgpt/trainer/cpgpt_trainer.py
cpgpt/utils/__init__.py
cpgpt/utils/instantiators.py
cpgpt/utils/logging_utils.py
cpgpt/utils/pylogger.py
cpgpt/utils/rich_utils.py
cpgpt/utils/utils.py
poetry.lock
cpgpt-0.0.7.dist-info/LICENSE
cpgpt-0.0.7.dist-info/METADATA
cpgpt-0.0.7.dist-info/WHEEL
cpgpt-0.0.7.dist-info/entry_points.txt
cpgpt-0.0.7.dist-info/RECORD
