Metadata-Version: 2.1
Name: CpGPT
Version: 0.0.7
Summary: CpGPT: A Foundation Model for DNA Methylation
License: Non-commercial
Author: Lucas Paulo de Lima Camillo
Author-email: lucas_camillo@alumni.brown.edu
Requires-Python: >=3.10,<3.14
Classifier: License :: Other/Proprietary License
Classifier: Programming Language :: Python :: 3
Classifier: Programming Language :: Python :: 3.10
Classifier: Programming Language :: Python :: 3.11
Classifier: Programming Language :: Python :: 3.12
Classifier: Programming Language :: Python :: 3.13
Requires-Dist: biopython (>=1.84,<2.0)
Requires-Dist: boto3 (>=1.37.15,<2.0.0)
Requires-Dist: fastapi (>=0.112.0,<0.115)
Requires-Dist: hydra-colorlog (>=1.2.0)
Requires-Dist: hydra-core (>=1.3.2)
Requires-Dist: ipywidgets (>=8.1.5)
Requires-Dist: lifelines (>=0.29.0)
Requires-Dist: lightning (>=2.2.0)
Requires-Dist: loguru (>=0.7.2)
Requires-Dist: pyarrow (==20.0.0)
Requires-Dist: pyfaidx (>=0.8.1.2)
Requires-Dist: rich (>=13.8.1)
Requires-Dist: rootutils (>=1.0.7,<2.0.0)
Requires-Dist: schedulefree (>=1.4,<2.0)
Requires-Dist: sqlitedict (>=2.1.0)
Requires-Dist: torch (>=2.2.0,<=2.6.0)
Requires-Dist: torchao (>=0.1.0)
Requires-Dist: torchmetrics (>=1.5.2)
Requires-Dist: torchtune (==0.3.1)
Requires-Dist: torchvision (>=0.20.1)
Requires-Dist: transformers (>=4.44.2)
Project-URL: homepage, https://github.com/lcamillo/CpGPT
Project-URL: repository, https://github.com/lcamillo/CpGPT
